[
  {
    "activityId": "AssessCrit001",
    "attributeId": "A134",
    "value": "Agent001",
    "evidenceDataName": "AssessCriterion",
    "attributeName": "wasAssociatedWith",
    "attributeType": "Agent",
    "lookupValue": "Steven Harrison"
  },
  {
    "activityId": "AssessCrit002",
    "attributeId": "A134",
    "value": "Agent001",
    "evidenceDataName": "AssessCriterion",
    "attributeName": "wasAssociatedWith",
    "attributeType": "Agent",
    "lookupValue": "Steven Harrison"
  },
  {
    "activityId": "AssessCrit003",
    "attributeId": "A134",
    "value": "Agent001",
    "evidenceDataName": "AssessCriterion",
    "attributeName": "wasAssociatedWith",
    "attributeType": "Agent",
    "lookupValue": "Steven Harrison"
  },
  {
    "activityId": "AssessCrit004",
    "attributeId": "A134",
    "value": "Agent001",
    "evidenceDataName": "AssessCriterion",
    "attributeName": "wasAssociatedWith",
    "attributeType": "Agent",
    "lookupValue": "Steven Harrison"
  },
  {
    "activityId": "AssessCrit005",
    "attributeId": "A134",
    "value": "Agent001",
    "evidenceDataName": "AssessCriterion",
    "attributeName": "wasAssociatedWith",
    "attributeType": "Agent",
    "lookupValue": "Steven Harrison"
  },
  {
    "activityId": "AssessCrit006",
    "attributeId": "A134",
    "value": "Agent001",
    "evidenceDataName": "AssessCriterion",
    "attributeName": "wasAssociatedWith",
    "attributeType": "Agent",
    "lookupValue": "Steven Harrison"
  },
  {
    "activityId": "AssessCrit006",
    "attributeId": "A134",
    "value": "Agent004",
    "evidenceDataName": "AssessCriterion",
    "attributeName": "wasAssociatedWith",
    "attributeType": "Agent",
    "lookupValue": "Noonan/Rasopathy WG (ClinGen)"
  },
  {
    "activityId": "AssessCrit007",
    "attributeId": "A134",
    "value": "Agent001",
    "evidenceDataName": "AssessCriterion",
    "attributeName": "wasAssociatedWith",
    "attributeType": "Agent",
    "lookupValue": "Steven Harrison"
  },
  {
    "activityId": "AssessCrit008",
    "attributeId": "A134",
    "value": "Agent001",
    "evidenceDataName": "AssessCriterion",
    "attributeName": "wasAssociatedWith",
    "attributeType": "Agent",
    "lookupValue": "Steven Harrison"
  },
  {
    "activityId": "AssessCrit009",
    "attributeId": "A134",
    "value": "Agent001",
    "evidenceDataName": "AssessCriterion",
    "attributeName": "wasAssociatedWith",
    "attributeType": "Agent",
    "lookupValue": "Steven Harrison"
  },
  {
    "activityId": "AssessCrit010",
    "attributeId": "A134",
    "value": "Agent003",
    "evidenceDataName": "AssessCriterion",
    "attributeName": "wasAssociatedWith",
    "attributeType": "Agent",
    "lookupValue": "Tasha Strande"
  },
  {
    "activityId": "AssessCrit010",
    "attributeId": "A134",
    "value": "Agent005",
    "evidenceDataName": "AssessCriterion",
    "attributeName": "wasAssociatedWith",
    "attributeType": "Agent",
    "lookupValue": "CSER Bake Off Project"
  },
  {
    "activityId": "AssessCrit011",
    "attributeId": "A134",
    "value": "Agent003",
    "evidenceDataName": "AssessCriterion",
    "attributeName": "wasAssociatedWith",
    "attributeType": "Agent",
    "lookupValue": "Tasha Strande"
  },
  {
    "activityId": "AssessCrit011",
    "attributeId": "A134",
    "value": "Agent005",
    "evidenceDataName": "AssessCriterion",
    "attributeName": "wasAssociatedWith",
    "attributeType": "Agent",
    "lookupValue": "CSER Bake Off Project"
  },
  {
    "activityId": "AssessCrit012",
    "attributeId": "A134",
    "value": "Agent001",
    "evidenceDataName": "AssessCriterion",
    "attributeName": "wasAssociatedWith",
    "attributeType": "Agent",
    "lookupValue": "Steven Harrison"
  },
  {
    "activityId": "AssessCrit012",
    "attributeId": "A134",
    "value": "Agent004",
    "evidenceDataName": "AssessCriterion",
    "attributeName": "wasAssociatedWith",
    "attributeType": "Agent",
    "lookupValue": "Noonan/Rasopathy WG (ClinGen)"
  },
  {
    "activityId": "AssessCrit013",
    "attributeId": "A134",
    "value": "Agent001",
    "evidenceDataName": "AssessCriterion",
    "attributeName": "wasAssociatedWith",
    "attributeType": "Agent",
    "lookupValue": "Steven Harrison"
  },
  {
    "activityId": "AssessCrit014",
    "attributeId": "A134",
    "value": "Agent001",
    "evidenceDataName": "AssessCriterion",
    "attributeName": "wasAssociatedWith",
    "attributeType": "Agent",
    "lookupValue": "Steven Harrison"
  },
  {
    "activityId": "AssessCrit015",
    "attributeId": "A134",
    "value": "Agent001",
    "evidenceDataName": "AssessCriterion",
    "attributeName": "wasAssociatedWith",
    "attributeType": "Agent",
    "lookupValue": "Steven Harrison"
  },
  {
    "activityId": "AssessCrit016",
    "attributeId": "A134",
    "value": "Agent003",
    "evidenceDataName": "AssessCriterion",
    "attributeName": "wasAssociatedWith",
    "attributeType": "Agent",
    "lookupValue": "Tasha Strande"
  },
  {
    "activityId": "AssessCrit017",
    "attributeId": "A134",
    "value": "Agent001",
    "evidenceDataName": "AssessCriterion",
    "attributeName": "wasAssociatedWith",
    "attributeType": "Agent",
    "lookupValue": "Steven Harrison"
  },
  {
    "activityId": "AssessCrit017",
    "attributeId": "A134",
    "value": "Agent004",
    "evidenceDataName": "AssessCriterion",
    "attributeName": "wasAssociatedWith",
    "attributeType": "Agent",
    "lookupValue": "Noonan/Rasopathy WG (ClinGen)"
  },
  {
    "activityId": "AssessCrit018",
    "attributeId": "A134",
    "value": "Agent001",
    "evidenceDataName": "AssessCriterion",
    "attributeName": "wasAssociatedWith",
    "attributeType": "Agent",
    "lookupValue": "Steven Harrison"
  },
  {
    "activityId": "AssessCrit019",
    "attributeId": "A134",
    "value": "Agent001",
    "evidenceDataName": "AssessCriterion",
    "attributeName": "wasAssociatedWith",
    "attributeType": "Agent",
    "lookupValue": "Steven Harrison"
  },
  {
    "activityId": "AssessCrit020",
    "attributeId": "A134",
    "value": "Agent001",
    "evidenceDataName": "AssessCriterion",
    "attributeName": "wasAssociatedWith",
    "attributeType": "Agent",
    "lookupValue": "Steven Harrison"
  },
  {
    "activityId": "AssessCrit021",
    "attributeId": "A134",
    "value": "Agent001",
    "evidenceDataName": "AssessCriterion",
    "attributeName": "wasAssociatedWith",
    "attributeType": "Agent",
    "lookupValue": "Steven Harrison"
  },
  {
    "activityId": "AssessCrit022",
    "attributeId": "A134",
    "value": "Agent001",
    "evidenceDataName": "AssessCriterion",
    "attributeName": "wasAssociatedWith",
    "attributeType": "Agent",
    "lookupValue": "Steven Harrison"
  },
  {
    "activityId": "AssessCrit023",
    "attributeId": "A134",
    "value": "Agent001",
    "evidenceDataName": "AssessCriterion",
    "attributeName": "wasAssociatedWith",
    "attributeType": "Agent",
    "lookupValue": "Steven Harrison"
  },
  {
    "activityId": "AssessCrit024",
    "attributeId": "A134",
    "value": "Agent001",
    "evidenceDataName": "AssessCriterion",
    "attributeName": "wasAssociatedWith",
    "attributeType": "Agent",
    "lookupValue": "Steven Harrison"
  },
  {
    "activityId": "AssessCrit025",
    "attributeId": "A134",
    "value": "Agent003",
    "evidenceDataName": "AssessCriterion",
    "attributeName": "wasAssociatedWith",
    "attributeType": "Agent",
    "lookupValue": "Tasha Strande"
  },
  {
    "activityId": "AssessCrit026",
    "attributeId": "A134",
    "value": "Agent003",
    "evidenceDataName": "AssessCriterion",
    "attributeName": "wasAssociatedWith",
    "attributeType": "Agent",
    "lookupValue": "Tasha Strande"
  },
  {
    "activityId": "AssessCrit027",
    "attributeId": "A134",
    "value": "Agent001",
    "evidenceDataName": "AssessCriterion",
    "attributeName": "wasAssociatedWith",
    "attributeType": "Agent",
    "lookupValue": "Steven Harrison"
  },
  {
    "activityId": "AssessCrit028",
    "attributeId": "A134",
    "value": "Agent006",
    "evidenceDataName": "AssessCriterion",
    "attributeName": "wasAssociatedWith",
    "attributeType": "Agent",
    "lookupValue": "Rajarshi Ghosh"
  },
  {
    "activityId": "AssessCrit029",
    "attributeId": "A134",
    "value": "Agent006",
    "evidenceDataName": "AssessCriterion",
    "attributeName": "wasAssociatedWith",
    "attributeType": "Agent",
    "lookupValue": "Rajarshi Ghosh"
  },
  {
    "activityId": "AssessCrit030",
    "attributeId": "A134",
    "value": "Agent001",
    "evidenceDataName": "AssessCriterion",
    "attributeName": "wasAssociatedWith",
    "attributeType": "Agent",
    "lookupValue": "Steven Harrison"
  },
  {
    "activityId": "AssessCrit031",
    "attributeId": "A134",
    "value": "Agent001",
    "evidenceDataName": "AssessCriterion",
    "attributeName": "wasAssociatedWith",
    "attributeType": "Agent",
    "lookupValue": "Steven Harrison"
  },
  {
    "activityId": "AssessCrit031",
    "attributeId": "A134",
    "value": "Agent005",
    "evidenceDataName": "AssessCriterion",
    "attributeName": "wasAssociatedWith",
    "attributeType": "Agent",
    "lookupValue": "CSER Bake Off Project"
  },
  {
    "activityId": "GenVarInterp032",
    "attributeId": "A134",
    "value": "Agent009",
    "evidenceDataName": "GenerateVariantInterpretation",
    "attributeName": "wasAssociatedWith",
    "attributeType": "Agent",
    "lookupValue": "CSER classifer #3"
  },
  {
    "activityId": "CapData033",
    "attributeId": "A134",
    "value": "Agent001",
    "evidenceDataName": "CaptureData",
    "attributeName": "wasAssociatedWith",
    "attributeType": "Agent",
    "lookupValue": "Steven Harrison"
  },
  {
    "activityId": "AssessCrit034",
    "attributeId": "A134",
    "value": "Agent006",
    "evidenceDataName": "AssessCriterion",
    "attributeName": "wasAssociatedWith",
    "attributeType": "Agent",
    "lookupValue": "Rajarshi Ghosh"
  },
  {
    "activityId": "AssessCrit034",
    "attributeId": "A134",
    "value": "Agent005",
    "evidenceDataName": "AssessCriterion",
    "attributeName": "wasAssociatedWith",
    "attributeType": "Agent",
    "lookupValue": "CSER Bake Off Project"
  },
  {
    "activityId": "AssessCrit035",
    "attributeId": "A134",
    "value": "Agent001",
    "evidenceDataName": "AssessCriterion",
    "attributeName": "wasAssociatedWith",
    "attributeType": "Agent",
    "lookupValue": "Steven Harrison"
  },
  {
    "activityId": "AssessCrit036",
    "attributeId": "A134",
    "value": "Agent001",
    "evidenceDataName": "AssessCriterion",
    "attributeName": "wasAssociatedWith",
    "attributeType": "Agent",
    "lookupValue": "Steven Harrison"
  },
  {
    "activityId": "AssessCrit037",
    "attributeId": "A134",
    "value": "Agent001",
    "evidenceDataName": "AssessCriterion",
    "attributeName": "wasAssociatedWith",
    "attributeType": "Agent",
    "lookupValue": "Steven Harrison"
  },
  {
    "activityId": "AssessCrit038",
    "attributeId": "A134",
    "value": "Agent001",
    "evidenceDataName": "AssessCriterion",
    "attributeName": "wasAssociatedWith",
    "attributeType": "Agent",
    "lookupValue": "Steven Harrison"
  },
  {
    "activityId": "AssessCrit039",
    "attributeId": "A134",
    "value": "Agent001",
    "evidenceDataName": "AssessCriterion",
    "attributeName": "wasAssociatedWith",
    "attributeType": "Agent",
    "lookupValue": "Steven Harrison"
  },
  {
    "activityId": "AssessCrit040",
    "attributeId": "A134",
    "value": "Agent002",
    "evidenceDataName": "AssessCriterion",
    "attributeName": "wasAssociatedWith",
    "attributeType": "Agent",
    "lookupValue": "Chris Bizon"
  },
  {
    "activityId": "AssessCrit041",
    "attributeId": "A134",
    "value": "Agent001",
    "evidenceDataName": "AssessCriterion",
    "attributeName": "wasAssociatedWith",
    "attributeType": "Agent",
    "lookupValue": "Steven Harrison"
  },
  {
    "activityId": "AssessCrit042",
    "attributeId": "A134",
    "value": "Agent006",
    "evidenceDataName": "AssessCriterion",
    "attributeName": "wasAssociatedWith",
    "attributeType": "Agent",
    "lookupValue": "Rajarshi Ghosh"
  },
  {
    "activityId": "AssessCrit042",
    "attributeId": "A134",
    "value": "Agent005",
    "evidenceDataName": "AssessCriterion",
    "attributeName": "wasAssociatedWith",
    "attributeType": "Agent",
    "lookupValue": "CSER Bake Off Project"
  },
  {
    "activityId": "AssessCrit043",
    "attributeId": "A134",
    "value": "Agent006",
    "evidenceDataName": "AssessCriterion",
    "attributeName": "wasAssociatedWith",
    "attributeType": "Agent",
    "lookupValue": "Rajarshi Ghosh"
  },
  {
    "activityId": "AssessCrit044",
    "attributeId": "A134",
    "value": "Agent001",
    "evidenceDataName": "AssessCriterion",
    "attributeName": "wasAssociatedWith",
    "attributeType": "Agent",
    "lookupValue": "Steven Harrison"
  },
  {
    "activityId": "GenVarInterp045",
    "attributeId": "A134",
    "value": "Agent010",
    "evidenceDataName": "GenerateVariantInterpretation",
    "attributeName": "wasAssociatedWith",
    "attributeType": "Agent",
    "lookupValue": "CSER classifer #6"
  },
  {
    "activityId": "AssessCrit046",
    "attributeId": "A134",
    "value": "Agent001",
    "evidenceDataName": "AssessCriterion",
    "attributeName": "wasAssociatedWith",
    "attributeType": "Agent",
    "lookupValue": "Steven Harrison"
  },
  {
    "activityId": "AssessCrit046",
    "attributeId": "A134",
    "value": "Agent005",
    "evidenceDataName": "AssessCriterion",
    "attributeName": "wasAssociatedWith",
    "attributeType": "Agent",
    "lookupValue": "CSER Bake Off Project"
  },
  {
    "activityId": "AssessCrit047",
    "attributeId": "A134",
    "value": "Agent001",
    "evidenceDataName": "AssessCriterion",
    "attributeName": "wasAssociatedWith",
    "attributeType": "Agent",
    "lookupValue": "Steven Harrison"
  },
  {
    "activityId": "AssessCrit048",
    "attributeId": "A134",
    "value": "Agent001",
    "evidenceDataName": "AssessCriterion",
    "attributeName": "wasAssociatedWith",
    "attributeType": "Agent",
    "lookupValue": "Steven Harrison"
  },
  {
    "activityId": "AssessCrit049",
    "attributeId": "A134",
    "value": "Agent001",
    "evidenceDataName": "AssessCriterion",
    "attributeName": "wasAssociatedWith",
    "attributeType": "Agent",
    "lookupValue": "Steven Harrison"
  },
  {
    "activityId": "AssessCrit050",
    "attributeId": "A134",
    "value": "Agent001",
    "evidenceDataName": "AssessCriterion",
    "attributeName": "wasAssociatedWith",
    "attributeType": "Agent",
    "lookupValue": "Steven Harrison"
  },
  {
    "activityId": "AssessCrit051",
    "attributeId": "A134",
    "value": "Agent001",
    "evidenceDataName": "AssessCriterion",
    "attributeName": "wasAssociatedWith",
    "attributeType": "Agent",
    "lookupValue": "Steven Harrison"
  },
  {
    "activityId": "AssessCrit052",
    "attributeId": "A134",
    "value": "Agent001",
    "evidenceDataName": "AssessCriterion",
    "attributeName": "wasAssociatedWith",
    "attributeType": "Agent",
    "lookupValue": "Steven Harrison"
  },
  {
    "activityId": "AssessCrit053",
    "attributeId": "A134",
    "value": "Agent001",
    "evidenceDataName": "AssessCriterion",
    "attributeName": "wasAssociatedWith",
    "attributeType": "Agent",
    "lookupValue": "Steven Harrison"
  },
  {
    "activityId": "AssessCrit054",
    "attributeId": "A134",
    "value": "Agent006",
    "evidenceDataName": "AssessCriterion",
    "attributeName": "wasAssociatedWith",
    "attributeType": "Agent",
    "lookupValue": "Rajarshi Ghosh"
  },
  {
    "activityId": "AssessCrit055",
    "attributeId": "A134",
    "value": "Agent006",
    "evidenceDataName": "AssessCriterion",
    "attributeName": "wasAssociatedWith",
    "attributeType": "Agent",
    "lookupValue": "Rajarshi Ghosh"
  },
  {
    "activityId": "AssessCrit055",
    "attributeId": "A134",
    "value": "Agent005",
    "evidenceDataName": "AssessCriterion",
    "attributeName": "wasAssociatedWith",
    "attributeType": "Agent",
    "lookupValue": "CSER Bake Off Project"
  },
  {
    "activityId": "AssessCrit056",
    "attributeId": "A134",
    "value": "Agent008",
    "evidenceDataName": "AssessCriterion",
    "attributeName": "wasAssociatedWith",
    "attributeType": "Agent",
    "lookupValue": "Marina DiStefano"
  },
  {
    "activityId": "AssessCrit057",
    "attributeId": "A134",
    "value": "Agent001",
    "evidenceDataName": "AssessCriterion",
    "attributeName": "wasAssociatedWith",
    "attributeType": "Agent",
    "lookupValue": "Steven Harrison"
  },
  {
    "activityId": "AssessCrit058",
    "attributeId": "A134",
    "value": "Agent008",
    "evidenceDataName": "AssessCriterion",
    "attributeName": "wasAssociatedWith",
    "attributeType": "Agent",
    "lookupValue": "Marina DiStefano"
  },
  {
    "activityId": "AssessCrit058",
    "attributeId": "A134",
    "value": "Agent005",
    "evidenceDataName": "AssessCriterion",
    "attributeName": "wasAssociatedWith",
    "attributeType": "Agent",
    "lookupValue": "CSER Bake Off Project"
  },
  {
    "activityId": "AssessCrit059",
    "attributeId": "A134",
    "value": "Agent008",
    "evidenceDataName": "AssessCriterion",
    "attributeName": "wasAssociatedWith",
    "attributeType": "Agent",
    "lookupValue": "Marina DiStefano"
  },
  {
    "activityId": "AssessCrit059",
    "attributeId": "A134",
    "value": "Agent005",
    "evidenceDataName": "AssessCriterion",
    "attributeName": "wasAssociatedWith",
    "attributeType": "Agent",
    "lookupValue": "CSER Bake Off Project"
  },
  {
    "activityId": "GenVarInterp060",
    "attributeId": "A134",
    "value": "Agent010",
    "evidenceDataName": "GenerateVariantInterpretation",
    "attributeName": "wasAssociatedWith",
    "attributeType": "Agent",
    "lookupValue": "CSER classifer #6"
  },
  {
    "activityId": "AssessCrit061",
    "attributeId": "A134",
    "value": "Agent008",
    "evidenceDataName": "AssessCriterion",
    "attributeName": "wasAssociatedWith",
    "attributeType": "Agent",
    "lookupValue": "Marina DiStefano"
  },
  {
    "activityId": "AssessCrit062",
    "attributeId": "A134",
    "value": "Agent008",
    "evidenceDataName": "AssessCriterion",
    "attributeName": "wasAssociatedWith",
    "attributeType": "Agent",
    "lookupValue": "Marina DiStefano"
  },
  {
    "activityId": "AssessCrit063",
    "attributeId": "A134",
    "value": "Agent001",
    "evidenceDataName": "AssessCriterion",
    "attributeName": "wasAssociatedWith",
    "attributeType": "Agent",
    "lookupValue": "Steven Harrison"
  },
  {
    "activityId": "AssessCrit064",
    "attributeId": "A134",
    "value": "Agent001",
    "evidenceDataName": "AssessCriterion",
    "attributeName": "wasAssociatedWith",
    "attributeType": "Agent",
    "lookupValue": "Steven Harrison"
  },
  {
    "activityId": "AssessCrit065",
    "attributeId": "A134",
    "value": "Agent001",
    "evidenceDataName": "AssessCriterion",
    "attributeName": "wasAssociatedWith",
    "attributeType": "Agent",
    "lookupValue": "Steven Harrison"
  },
  {
    "activityId": "AssessCrit066",
    "attributeId": "A134",
    "value": "Agent006",
    "evidenceDataName": "AssessCriterion",
    "attributeName": "wasAssociatedWith",
    "attributeType": "Agent",
    "lookupValue": "Rajarshi Ghosh"
  },
  {
    "activityId": "AssessCrit067",
    "attributeId": "A134",
    "value": "Agent006",
    "evidenceDataName": "AssessCriterion",
    "attributeName": "wasAssociatedWith",
    "attributeType": "Agent",
    "lookupValue": "Rajarshi Ghosh"
  },
  {
    "activityId": "AssessCrit068",
    "attributeId": "A134",
    "value": "Agent008",
    "evidenceDataName": "AssessCriterion",
    "attributeName": "wasAssociatedWith",
    "attributeType": "Agent",
    "lookupValue": "Marina DiStefano"
  },
  {
    "activityId": "AssessCrit069",
    "attributeId": "A134",
    "value": "Agent008",
    "evidenceDataName": "AssessCriterion",
    "attributeName": "wasAssociatedWith",
    "attributeType": "Agent",
    "lookupValue": "Marina DiStefano"
  },
  {
    "activityId": "AssessCrit070",
    "attributeId": "A134",
    "value": "Agent008",
    "evidenceDataName": "AssessCriterion",
    "attributeName": "wasAssociatedWith",
    "attributeType": "Agent",
    "lookupValue": "Marina DiStefano"
  },
  {
    "activityId": "AssessCrit071",
    "attributeId": "A134",
    "value": "Agent008",
    "evidenceDataName": "AssessCriterion",
    "attributeName": "wasAssociatedWith",
    "attributeType": "Agent",
    "lookupValue": "Marina DiStefano"
  },
  {
    "activityId": "AssessCrit072",
    "attributeId": "A134",
    "value": "Agent008",
    "evidenceDataName": "AssessCriterion",
    "attributeName": "wasAssociatedWith",
    "attributeType": "Agent",
    "lookupValue": "Marina DiStefano"
  },
  {
    "activityId": "CapData073",
    "attributeId": "A134",
    "value": "Agent001",
    "evidenceDataName": "CaptureData",
    "attributeName": "wasAssociatedWith",
    "attributeType": "Agent",
    "lookupValue": "Steven Harrison"
  },
  {
    "activityId": "CapData074",
    "attributeId": "A134",
    "value": "Agent008",
    "evidenceDataName": "CaptureData",
    "attributeName": "wasAssociatedWith",
    "attributeType": "Agent",
    "lookupValue": "Marina DiStefano"
  },
  {
    "activityId": "CapData075",
    "attributeId": "A134",
    "value": "Agent001",
    "evidenceDataName": "CaptureData",
    "attributeName": "wasAssociatedWith",
    "attributeType": "Agent",
    "lookupValue": "Steven Harrison"
  },
  {
    "activityId": "CapData076",
    "attributeId": "A134",
    "value": "Agent008",
    "evidenceDataName": "CaptureData",
    "attributeName": "wasAssociatedWith",
    "attributeType": "Agent",
    "lookupValue": "Marina DiStefano"
  },
  {
    "activityId": "CapData077",
    "attributeId": "A134",
    "value": "Agent001",
    "evidenceDataName": "CaptureData",
    "attributeName": "wasAssociatedWith",
    "attributeType": "Agent",
    "lookupValue": "Steven Harrison"
  },
  {
    "activityId": "CapData078",
    "attributeId": "A134",
    "value": "Agent008",
    "evidenceDataName": "CaptureData",
    "attributeName": "wasAssociatedWith",
    "attributeType": "Agent",
    "lookupValue": "Marina DiStefano"
  },
  {
    "activityId": "CapData079",
    "attributeId": "A134",
    "value": "Agent001",
    "evidenceDataName": "CaptureData",
    "attributeName": "wasAssociatedWith",
    "attributeType": "Agent",
    "lookupValue": "Steven Harrison"
  },
  {
    "activityId": "CapData080",
    "attributeId": "A134",
    "value": "Agent008",
    "evidenceDataName": "CaptureData",
    "attributeName": "wasAssociatedWith",
    "attributeType": "Agent",
    "lookupValue": "Marina DiStefano"
  },
  {
    "activityId": "CapData081",
    "attributeId": "A134",
    "value": "Agent001",
    "evidenceDataName": "CaptureData",
    "attributeName": "wasAssociatedWith",
    "attributeType": "Agent",
    "lookupValue": "Steven Harrison"
  },
  {
    "activityId": "AssessCrit082",
    "attributeId": "A134",
    "value": "Agent008",
    "evidenceDataName": "AssessCriterion",
    "attributeName": "wasAssociatedWith",
    "attributeType": "Agent",
    "lookupValue": "Marina DiStefano"
  },
  {
    "activityId": "AssessCrit083",
    "attributeId": "A134",
    "value": "Agent008",
    "evidenceDataName": "AssessCriterion",
    "attributeName": "wasAssociatedWith",
    "attributeType": "Agent",
    "lookupValue": "Marina DiStefano"
  },
  {
    "activityId": "AssessCrit084",
    "attributeId": "A134",
    "value": "Agent008",
    "evidenceDataName": "AssessCriterion",
    "attributeName": "wasAssociatedWith",
    "attributeType": "Agent",
    "lookupValue": "Marina DiStefano"
  },
  {
    "activityId": "AssessCrit085",
    "attributeId": "A134",
    "value": "Agent006",
    "evidenceDataName": "AssessCriterion",
    "attributeName": "wasAssociatedWith",
    "attributeType": "Agent",
    "lookupValue": "Rajarshi Ghosh"
  },
  {
    "activityId": "GenVarInterp086",
    "attributeId": "A134",
    "value": "Agent010",
    "evidenceDataName": "GenerateVariantInterpretation",
    "attributeName": "wasAssociatedWith",
    "attributeType": "Agent",
    "lookupValue": "CSER classifer #6"
  },
  {
    "activityId": "AssessCrit087",
    "attributeId": "A134",
    "value": "Agent008",
    "evidenceDataName": "AssessCriterion",
    "attributeName": "wasAssociatedWith",
    "attributeType": "Agent",
    "lookupValue": "Marina DiStefano"
  },
  {
    "activityId": "AssessCrit088",
    "attributeId": "A134",
    "value": "Agent008",
    "evidenceDataName": "AssessCriterion",
    "attributeName": "wasAssociatedWith",
    "attributeType": "Agent",
    "lookupValue": "Marina DiStefano"
  },
  {
    "activityId": "AssessCrit089",
    "attributeId": "A134",
    "value": "Agent008",
    "evidenceDataName": "AssessCriterion",
    "attributeName": "wasAssociatedWith",
    "attributeType": "Agent",
    "lookupValue": "Marina DiStefano"
  },
  {
    "activityId": "AssessCrit090",
    "attributeId": "A134",
    "value": "Agent008",
    "evidenceDataName": "AssessCriterion",
    "attributeName": "wasAssociatedWith",
    "attributeType": "Agent",
    "lookupValue": "Marina DiStefano"
  },
  {
    "activityId": "AssessCrit091",
    "attributeId": "A134",
    "value": "Agent008",
    "evidenceDataName": "AssessCriterion",
    "attributeName": "wasAssociatedWith",
    "attributeType": "Agent",
    "lookupValue": "Marina DiStefano"
  },
  {
    "activityId": "AssessCrit092",
    "attributeId": "A134",
    "value": "Agent008",
    "evidenceDataName": "AssessCriterion",
    "attributeName": "wasAssociatedWith",
    "attributeType": "Agent",
    "lookupValue": "Marina DiStefano"
  },
  {
    "activityId": "AssessCrit093",
    "attributeId": "A134",
    "value": "Agent008",
    "evidenceDataName": "AssessCriterion",
    "attributeName": "wasAssociatedWith",
    "attributeType": "Agent",
    "lookupValue": "Marina DiStefano"
  },
  {
    "activityId": "AssessCrit094",
    "attributeId": "A134",
    "value": "Agent008",
    "evidenceDataName": "AssessCriterion",
    "attributeName": "wasAssociatedWith",
    "attributeType": "Agent",
    "lookupValue": "Marina DiStefano"
  },
  {
    "activityId": "AssessCrit095",
    "attributeId": "A134",
    "value": "Agent008",
    "evidenceDataName": "AssessCriterion",
    "attributeName": "wasAssociatedWith",
    "attributeType": "Agent",
    "lookupValue": "Marina DiStefano"
  },
  {
    "activityId": "AssessCrit096",
    "attributeId": "A134",
    "value": "Agent008",
    "evidenceDataName": "AssessCriterion",
    "attributeName": "wasAssociatedWith",
    "attributeType": "Agent",
    "lookupValue": "Marina DiStefano"
  },
  {
    "activityId": "AssessCrit097",
    "attributeId": "A134",
    "value": "Agent008",
    "evidenceDataName": "AssessCriterion",
    "attributeName": "wasAssociatedWith",
    "attributeType": "Agent",
    "lookupValue": "Marina DiStefano"
  },
  {
    "activityId": "AssessCrit098",
    "attributeId": "A134",
    "value": "Agent008",
    "evidenceDataName": "AssessCriterion",
    "attributeName": "wasAssociatedWith",
    "attributeType": "Agent",
    "lookupValue": "Marina DiStefano"
  },
  {
    "activityId": "AssessCrit099",
    "attributeId": "A134",
    "value": "Agent008",
    "evidenceDataName": "AssessCriterion",
    "attributeName": "wasAssociatedWith",
    "attributeType": "Agent",
    "lookupValue": "Marina DiStefano"
  },
  {
    "activityId": "AssessCrit100",
    "attributeId": "A134",
    "value": "Agent001",
    "evidenceDataName": "AssessCriterion",
    "attributeName": "wasAssociatedWith",
    "attributeType": "Agent",
    "lookupValue": "Steven Harrison"
  },
  {
    "activityId": "AssessCrit101",
    "attributeId": "A134",
    "value": "Agent008",
    "evidenceDataName": "AssessCriterion",
    "attributeName": "wasAssociatedWith",
    "attributeType": "Agent",
    "lookupValue": "Marina DiStefano"
  },
  {
    "activityId": "AssessCrit102",
    "attributeId": "A134",
    "value": "Agent008",
    "evidenceDataName": "AssessCriterion",
    "attributeName": "wasAssociatedWith",
    "attributeType": "Agent",
    "lookupValue": "Marina DiStefano"
  },
  {
    "activityId": "AssessCrit103",
    "attributeId": "A134",
    "value": "Agent008",
    "evidenceDataName": "AssessCriterion",
    "attributeName": "wasAssociatedWith",
    "attributeType": "Agent",
    "lookupValue": "Marina DiStefano"
  },
  {
    "activityId": "GenVarInterp104",
    "attributeId": "A134",
    "value": "Agent011",
    "evidenceDataName": "GenerateVariantInterpretation",
    "attributeName": "wasAssociatedWith",
    "attributeType": "Agent",
    "lookupValue": "Gene Geneticist"
  },
  {
    "activityId": "GenVarInterp105",
    "attributeId": "A134",
    "value": "Agent012",
    "evidenceDataName": "GenerateVariantInterpretation",
    "attributeName": "wasAssociatedWith",
    "attributeType": "Agent",
    "lookupValue": "George Geneticist"
  }
]