[
  {
    "subjectId": "Synm001",
    "attributeId": "A134",
    "value": "Across all published data (and LMM data) with hearing loss.",
    "attribute": "description",
    "attributeType": "String"
  },
  {
    "subjectId": "Synm002",
    "attributeId": "A134",
    "value": "Case group is composed of cases from six cohorts from the GENIUS T2D consortium.  Case status is defined per-cohort.",
    "attribute": "description",
    "attributeType": "String"
  },
  {
    "subjectId": "Synm003",
    "attributeId": "A134",
    "value": "Controls group is composed of controls from six cohorts from the GENIUS T2D consortium.  Controls status is defined per-cohort.",
    "attribute": "description",
    "attributeType": "String"
  }
]